tests/__init__.py
tests/test_address_handler.py
tests/test_api_handler.py
tests/test_base_handler.py
tests/test_block_handler.py
tests/test_client.py
tests/test_contract_handler.py
tests/test_market_handler.py
tests/test_signature_handler.py
tests/test_token_handler.py
tests/test_transaction_handler.py
tests/test_websocket.py
web3data/__init__.py
web3data/chains.py
web3data/client.py
web3data/exceptions.py
web3data/handlers/__init__.py
web3data/handlers/address.py
web3data/handlers/api.py
web3data/handlers/base.py
web3data/handlers/block.py
web3data/handlers/contract.py
web3data/handlers/market.py
web3data/handlers/signature.py
web3data/handlers/token.py
web3data/handlers/transaction.py
web3data/handlers/websocket.py
web3data-0.1.7.dist-info/AUTHORS.rst
web3data-0.1.7.dist-info/LICENSE
web3data-0.1.7.dist-info/METADATA
web3data-0.1.7.dist-info/WHEEL
web3data-0.1.7.dist-info/top_level.txt
web3data-0.1.7.dist-info/RECORD
