Metadata-Version: 2.1
Name: web3data
Version: 0.1.7
Summary: A Python library for the Amberdata web3 API
Home-page: https://github.com/dmuhs/web3data-py
Author: Dominik Muhs
Author-email: dmuhs@protonmail.ch
License: MIT license
Keywords: web3data,web3data-py,amberdata,ethereum,bitcoin,stellar,rinkeby,aion,litecoin,zcash
Platform: UNKNOWN
Classifier: Development Status :: 4 - Beta
Classifier: License :: OSI Approved :: MIT License
Classifier: Natural Language :: English
Classifier: Intended Audience :: Developers
Classifier: Intended Audience :: Education
Classifier: Intended Audience :: Information Technology
Classifier: Intended Audience :: Financial and Insurance Industry
Classifier: Topic :: Security
Classifier: Topic :: Software Development :: Libraries :: Python Modules
Classifier: Topic :: Office/Business :: Financial
Classifier: Topic :: Utilities
Classifier: Typing :: Typed
Classifier: Operating System :: OS Independent
Classifier: Programming Language :: Python :: 3
Classifier: Programming Language :: Python :: 3.6
Classifier: Programming Language :: Python :: 3.7
Classifier: Programming Language :: Python :: 3.8
Classifier: Programming Language :: Python :: Implementation :: PyPy
Requires-Dist: requests (==2.25.1)
Requires-Dist: websocket-client (==0.57.0)
